{
    "fluentMethods": true,
    "relationships": [],
    "fields": [
        {
            "fieldName": "nome",
            "fieldType": "String",
            "fieldValidateRules": [
                "required"
            ]
        },
        {
            "fieldName": "dataprimeiroregistro",
            "fieldType": "LocalDate",
            "fieldValidateRules": [
                "required"
            ]
        },
        {
            "fieldName": "dataultimoregistro",
            "fieldType": "LocalDate",
            "fieldValidateRules": [
                "required"
            ]
        }
    ],
    "changelogDate": "20170823234226",
    "entityTableName": "consultores",
    "dto": "no",
    "pagination": "pagination",
    "service": "no"
}